{
  "surah": 111,
  "name": "Al-Masad",
  "translator": "Sahih International",
  "total_ayah": 5,
  "ayahs": [
    {
      "number": 1,
      "text": "May the hands of Abū Lahab be ruined, and ruined is he."
    },
    {
      "number": 2,
      "text": "His wealth will not avail him or that which he gained."
    },
    {
      "number": 3,
      "text": "He will [enter to] burn in a Fire of [blazing] flame"
    },
    {
      "number": 4,
      "text": "And his wife [as well] - the carrier of firewood."
    },
    {
      "number": 5,
      "text": "Around her neck is a rope of [twisted] fiber."
    }
  ]
}
